personInfo_package/__init__.py
personInfo_package/main.py
personInfo_package-1.0.0.dist-info/LICENSE.txt
personInfo_package-1.0.0.dist-info/METADATA
personInfo_package-1.0.0.dist-info/WHEEL
personInfo_package-1.0.0.dist-info/top_level.txt
personInfo_package-1.0.0.dist-info/RECORD
